fidget/__init__.py
fidget/backend/QtCore.py
fidget/backend/QtGui.py
fidget/backend/QtWidgets.py
fidget/backend/Resources.py
fidget/backend/__init__.py
fidget/backend/_resources.py
fidget/backend/preference.py
fidget/backend/qtbackend.py
fidget/core/__init__.py
fidget/core/__util__.py
fidget/core/code_editor.py
fidget/core/fidget.py
fidget/core/fidget_value.py
fidget/core/highlighter.py
fidget/core/plaintext_adapter.py
fidget/core/primitive_questions.py
fidget/core/user_util.py
fidget/widgets/__init__.py
fidget/widgets/__util__.py
fidget/widgets/checkbox.py
fidget/widgets/combo.py
fidget/widgets/compound.py
fidget/widgets/confirmer.py
fidget/widgets/const_label.py
fidget/widgets/converter.py
fidget/widgets/dict_.py
fidget/widgets/dir_path.py
fidget/widgets/discrete.py
fidget/widgets/edit_combo.py
fidget/widgets/file_path.py
fidget/widgets/idiomatic_inner.py
fidget/widgets/label.py
fidget/widgets/line.py
fidget/widgets/mapping.py
fidget/widgets/matrix.py
fidget/widgets/minimalist.py
fidget/widgets/multi_file.py
fidget/widgets/optional.py
fidget/widgets/rawstring.py
fidget/widgets/spin.py
fidget/widgets/stacked.py
fidget/widgets/tabbed.py
fidget/widgets/table.py
fidget/widgets/text.py
fidget/widgets/tuple_.py
fidget/widgets/user_util.py
fidget-0.1.3.dist-info/LICENSE.txt
fidget-0.1.3.dist-info/METADATA
fidget-0.1.3.dist-info/WHEEL
fidget-0.1.3.dist-info/top_level.txt
fidget-0.1.3.dist-info/RECORD
