Metadata-Version: 2.1
Name: fidget
Version: 0.1.3
Summary: Fidget is an adapter of Qt into a functional-style interface. Fidget can be used seamlessly with PySide6, PySide2, PyQt5. Fidget is designed to create an effortless and rich UI for data science and analysis.
Home-page: https://github.com/talos-gis/Fidget
Author: Ben Avrahami
Author-email: avrahami.ben@gmail.com
Maintainer: Idan Miara
Maintainer-email: idan@miara.com
License: MIT
Platform: UNKNOWN
Classifier: Development Status :: 5 - Production/Stable
Classifier: Intended Audience :: Developers
Classifier: License :: OSI Approved :: MIT License
Classifier: Operating System :: OS Independent
Classifier: Programming Language :: Python :: 3
Requires-Python: >=3.7.0
License-File: LICENSE.txt
Provides-Extra: pyqt
Requires-Dist: PyQt5 ; extra == 'pyqt'
Provides-Extra: pyqt5
Requires-Dist: PyQt5 ; extra == 'pyqt5'
Provides-Extra: pyside
Requires-Dist: PySide6 ; extra == 'pyside'
Provides-Extra: pyside2
Requires-Dist: PySide2 ; extra == 'pyside2'
Provides-Extra: pyside6
Requires-Dist: PySide6 ; extra == 'pyside6'
Provides-Extra: qt
Requires-Dist: PySide6 ; extra == 'qt'
